LICENSE.txt
MANIFEST.in
README.rst
setup.py
hash_benchmark/__init__.py
hash_benchmark/models.py
hash_benchmark.egg-info/PKG-INFO
hash_benchmark.egg-info/SOURCES.txt
hash_benchmark.egg-info/dependency_links.txt
hash_benchmark.egg-info/not-zip-safe
hash_benchmark.egg-info/requires.txt
hash_benchmark.egg-info/top_level.txt
hash_benchmark/management/__init__.py
hash_benchmark/management/commands/__init__.py
hash_benchmark/management/commands/hash_benchmark.py