Metadata-Version: 1.1
Name: hash-benchmark
Version: 0.2.0
Summary: Simple management commands for benchmarking a Django project's hash settings
Home-page: https://github.com/mkoistinen/hash_benchmark
Author: Martin Koistinen
Author-email: mkoistinen@gmail.com
License: LICENSE.txt
Platform: OS Independent
Classifier: Development Status :: 5 - Production/Stable
Classifier: Environment :: Web Environment
Classifier: Framework :: Django
Classifier: Intended Audience :: Developers
Classifier: License :: OSI Approved :: BSD License
Classifier: Operating System :: OS Independent
Classifier: Programming Language :: Python
Classifier: Topic :: Communications
Classifier: Topic :: Internet :: WWW/HTTP :: Dynamic Content
Classifier: Programming Language :: Python :: 2.7
